djangocms_call_to_action
