Metadata-Version: 2.1
Name: djangocms-call-to-action
Version: 0.0.2
Summary: This djangocms plugin allows you to create Call To Action (CTA) indicators, to display them as buttons in a Django CMS plugin, to track user click on these buttons on a GA conversion tunnel. Each CTA is linked with a fobi form which registers the user email in a given mailing list.
Home-page: https://gitlab.com/kapt/djangocms-call-to-action
Author: Dev Kapt
Author-email: dev@kapt.mobi
License: UNKNOWN
Platform: UNKNOWN
Classifier: Environment :: Web Environment
Classifier: Framework :: Django
Classifier: Intended Audience :: Developers
Classifier: License :: OSI Approved :: GNU General Public License v3 (GPLv3)
Classifier: Programming Language :: Python
Classifier: Programming Language :: Python :: 3
Classifier: Programming Language :: Python :: 3 :: Only
Classifier: Programming Language :: Python :: 3.7
Classifier: Programming Language :: Python :: 3.8
Classifier: Topic :: Internet :: WWW/HTTP
Classifier: Topic :: Internet :: WWW/HTTP :: Dynamic Content
